genie_flow/__init__.py
genie_flow/app.py
genie_flow/environment.py
genie_flow/genie.py
genie_flow/mongo.py
genie_flow/session.py
genie_flow/session_lock.py
genie_flow/utils.py
genie_flow/celery/__init__.py
genie_flow/celery/compiler.py
genie_flow/celery/progress.py
genie_flow/celery/transition.py
genie_flow/containers/__init__.py
genie_flow/containers/core.py
genie_flow/containers/genieflow.py
genie_flow/containers/perm_persistence.py
genie_flow/containers/persistence.py
genie_flow/model/__init__.py
genie_flow/model/api.py
genie_flow/model/dialogue.py
genie_flow/model/persistence.py
genie_flow/model/secondary_store.py
genie_flow/model/template.py
genie_flow/model/types.py
genie_flow/model/user.py
genie_flow/model/versioned.py
genie_flow-0.11.1.dist-info/licenses/NOTICES
genie_flow-0.11.1.dist-info/METADATA
genie_flow-0.11.1.dist-info/WHEEL
genie_flow-0.11.1.dist-info/top_level.txt
genie_flow-0.11.1.dist-info/RECORD
