Metadata-Version: 2.4
Name: genie_flow
Version: 0.11.1
Summary: Core classes for Genie Flow
Maintainer-email: Willem van Asperen <willem.van.asperen@paconsulting.com>
License-Expression: Apache-2.0
Project-URL: Homepage, https://genieversum.github.io
Project-URL: Repository, https://github.com/genieversum/genie-flow
Classifier: Development Status :: 5 - Production/Stable
Classifier: Intended Audience :: Developers
Classifier: Programming Language :: Python :: 3
Classifier: Programming Language :: Python :: 3.11
Classifier: Programming Language :: Python :: 3.12
Classifier: Operating System :: OS Independent
Classifier: Framework :: Celery
Classifier: Framework :: FastAPI
Classifier: Framework :: Pydantic
Classifier: Topic :: Communications :: Chat
Classifier: Topic :: Software Development :: Libraries :: Application Frameworks
Classifier: Topic :: Scientific/Engineering :: Artificial Intelligence
Classifier: Typing :: Typed
Requires-Python: >=3.11.0
License-File: NOTICES
Requires-Dist: genie-flow-invoker~=0.7.3
Requires-Dist: loguru~=0.7
Requires-Dist: python-statemachine~=2.3
Requires-Dist: pydantic~=2.11
Requires-Dist: jinja2~=3.1
Requires-Dist: fastapi~=0.115
Requires-Dist: celery~=5.5
Requires-Dist: gevent~=25.9.1
Requires-Dist: redis~=5.2
Requires-Dist: python-redis-lock~=4.0
Requires-Dist: dependency-injector~=4.42
Requires-Dist: jmespath-community~=1.1
Requires-Dist: python-snappy~=0.7
Requires-Dist: ulid-py~=1.1
Requires-Dist: pyaml~=25.1
Requires-Dist: pymongo~=4.12.1
Requires-Dist: uvicorn==0.34
Provides-Extra: test
Requires-Dist: pytest; extra == "test"
Requires-Dist: pytest-docker; extra == "test"
Dynamic: license-file
